{
  "unversionedId": "Problem Solving/BOJ/알파벳 갯수",
  "id": "Problem Solving/BOJ/알파벳 갯수",
  "title": "10808. 알파벳 개수",
  "description": "문제",
  "source": "@site/docs/Problem Solving/BOJ/10808. 알파벳 갯수.md",
  "sourceDirName": "Problem Solving/BOJ",
  "slug": "/Problem Solving/BOJ/알파벳 갯수",
  "permalink": "/docs/Problem Solving/BOJ/알파벳 갯수",
  "draft": false,
  "tags": [],
  "version": "current",
  "sidebarPosition": 10808,
  "frontMatter": {},
  "sidebar": "problemSolving",
  "previous": {
    "title": "2979. 트럭 주차",
    "permalink": "/docs/Problem Solving/BOJ/트럭 주차"
  },
  "next": {
    "title": "10988. 팰린드롬인지 확인하기",
    "permalink": "/docs/Problem Solving/BOJ/팰린드롬인지 확인하기"
  }
}