{
  "pluginId": "default",
  "version": "current",
  "label": "Next",
  "banner": null,
  "badge": false,
  "noIndex": false,
  "className": "docs-version-current",
  "isLast": true,
  "docsSidebars": {
    "tutorialSidebar": [
      {
        "type": "category",
        "label": "Problem Solving",
        "collapsible": true,
        "collapsed": true,
        "items": [
          {
            "type": "link",
            "label": "About",
            "href": "/docs/Problem Solving/about",
            "docId": "Problem Solving/about"
          },
          {
            "type": "category",
            "label": "LeetCode",
            "collapsible": true,
            "collapsed": true,
            "items": [
              {
                "type": "link",
                "label": "125. Valid Palindrome",
                "href": "/docs/Problem Solving/LeetCode/valid-palindrome",
                "docId": "Problem Solving/LeetCode/valid-palindrome"
              },
              {
                "type": "link",
                "label": "561. Array Partition",
                "href": "/docs/Problem Solving/LeetCode/array-partition",
                "docId": "Problem Solving/LeetCode/array-partition"
              }
            ]
          }
        ]
      }
    ]
  },
  "docs": {
    "Problem Solving/about": {
      "id": "Problem Solving/about",
      "title": "About",
      "description": "- LeetCode : BonJunKu",
      "sidebar": "tutorialSidebar"
    },
    "Problem Solving/LeetCode/array-partition": {
      "id": "Problem Solving/LeetCode/array-partition",
      "title": "561. Array Partition",
      "description": "Description",
      "sidebar": "tutorialSidebar"
    },
    "Problem Solving/LeetCode/valid-palindrome": {
      "id": "Problem Solving/LeetCode/valid-palindrome",
      "title": "125. Valid Palindrome",
      "description": "Description",
      "sidebar": "tutorialSidebar"
    }
  }
}